openlimit_lite/__init__.py
openlimit_lite/rate_limiters.py
openlimit_lite/buckets/__init__.py
openlimit_lite/buckets/bucket.py
openlimit_lite/buckets/buckets.py
openlimit_lite/utilities/__init__.py
openlimit_lite/utilities/context_decorators.py
openlimit_lite/utilities/token_counters.py
openlimit_lite-1.3.1.dist-info/LICENSE
openlimit_lite-1.3.1.dist-info/METADATA
openlimit_lite-1.3.1.dist-info/WHEEL
openlimit_lite-1.3.1.dist-info/top_level.txt
openlimit_lite-1.3.1.dist-info/RECORD
