Metadata-Version: 2.1
Name: openlimit_lite
Version: 1.3.1
Summary: Rate limiter for the OpenAI API
Author-email: alexliao <support@dragoneye.ai>, shobrook <shobrookj@gmail.com>
Project-URL: Homepage, https://github.com/dragoneyeAI/openlimit-lite
Keywords: openai,rate-limit,limit,api,request,token,leaky-bucket,gcra,asyncio
Requires-Python: >=3.0
License-File: LICENSE
Requires-Dist: tiktoken
